{
    "advanceWidth": 1000,
    "advanceHeight": 1000,
    "verticalOrigin": 880,
    "contours": [
        [
            {"x": 321,"y": 8 + 699,"on": true},
            {"x": 321,"y": 8 + 610,"on": true},
            {"x": 331,"y": 8 + 610,"on": true},
            {"x": 355,"y": 8 + 610,"on": false},
            {"x": 383,"y": 8 + 619,"on": false},
            {"x": 383,"y": 8 + 627,"on": true},
            {"x": 383,"y": 8 + 699,"on": true},
            {"x": 621,"y": 8 + 699,"on": true},
            {"x": 621,"y": 20 + 612,"on": true},
            {"x": 632,"y": 20 + 612,"on": true},
            {"x": 663,"y": 20 + 613,"on": false},
            {"x": 684,"y": 20 + 625,"on": false},
            {"x": 684,"y": 20 + 631,"on": true},
            {"x": 684,"y": 8 + 699,"on": true},
            {"x": 932,"y": 8 + 699,"on": true},
            {"x": 946,"y": 8 + 699,"on": false},
            {"x": 956,"y": 8 + 704,"on": false},
            {"x": 958,"y": 8 + 715,"on": true},
            {"x": 927,"y": 745,"on": false},
            {"x": 873,"y": 787,"on": false},
            {"x": 873,"y": 787,"on": true},
            {"x": 826,"y": 8 + 729,"on": true},
            {"x": 684,"y": 8 + 729,"on": true},
            {"x": 684,"y": 8 + 800,"on": true},
            {"x": 709,"y": 8 + 803,"on": false},
            {"x": 718,"y": 8 + 813,"on": false},
            {"x": 720,"y": 8 + 827,"on": true},
            {"x": 621,"y": 8 + 837,"on": true},
            {"x": 621,"y": 8 + 729,"on": true},
            {"x": 383,"y": 8 + 729,"on": true},
            {"x": 383,"y": 800,"on": true},
            {"x": 408,"y": 803,"on": false},
            {"x": 417,"y": 813,"on": false},
            {"x": 419,"y": 827,"on": true},
            {"x": 321,"y": 837,"on": true},
            {"x": 321,"y": 8 + 729,"on": true},
            {"x":  53,"y": 8 + 729,"on": true},
            {"x":  59,"y": 8 + 699,"on": true}
        ], [
            {"x": 702,"y": 41,"on": true},
            {"x": 735,"y": 41,"on": false},
            {"x": 757,"y": 55,"on": false},
            {"x": 757,"y": 59,"on": true},
            {"x": 757,"y": 369,"on": true},
            {"x": 931,"y": 369,"on": true},
            {"x": 945,"y": 369,"on": false},
            {"x": 955,"y": 374,"on": false},
            {"x": 957,"y": 385,"on": true},
            {"x": 923,"y": 417,"on": false},
            {"x": 869,"y": 459,"on": false},
            {"x": 869,"y": 459,"on": true},
            {"x": 821,"y": 399,"on": true},
            {"x": 488,"y": 399,"on": true},
            {"x": 488,"y": 528,"on": true},
            {"x": 614,"y": 538,"on": false},
            {"x": 750,"y": 562,"on": false},
            {"x": 840,"y": 583,"on": true},
            {"x": 864,"y": 574,"on": false},
            {"x": 881,"y": 573,"on": false},
            {"x": 890,"y": 582,"on": true},
            {"x": 814,"y": 654,"on": true},
            {"x": 743,"y": 622,"on": false},
            {"x": 615,"y": 580,"on": false},
            {"x": 499,"y": 553,"on": true},
            {"x": 425,"y": 577,"on": true},
            {"x": 425,"y": 394,"on": true},
            {"x": 425,"y": 278,"on": false},
            {"x": 412,"y": 154,"on": false},
            {"x": 313,"y": 53,"on": true},
            {"x": 326,"y": 41,"on": true},
            {"x": 463,"y": 130,"on": false},
            {"x": 485,"y": 263,"on": false},
            {"x": 488,"y": 369,"on": true},
            {"x": 692,"y": 369,"on": true},
            {"x": 692,"y": 41,"on": true}
        ],
        [
            {"x": 108,"y": 650,"on": true},
            {"x": 151,"y": 619,"on": false},
            {"x": 207,"y": 563,"on": false},
            {"x": 224,"y": 517,"on": true},
            {"x": 293,"y": 481,"on": false},
            {"x": 328,"y": 619,"on": false},
            {"x": 118,"y": 659,"on": true}
        ],
        [
            {"x": 54,"y": 487,"on": true},
            {"x": 99,"y": 459,"on": false},
            {"x": 156,"y": 406,"on": false},
            {"x": 177,"y": 362,"on": true},
            {"x": 247,"y": 330,"on": false},
            {"x": 275,"y": 468,"on": false},
            {"x": 62,"y": 496,"on": true}
        ],
        [
            {"x": 240,"y": 219,"on": true},
            {"x": 267,"y": 223,"on": false},
            {"x": 281,"y": 231,"on": false},
            {"x": 288,"y": 238,"on": true},
            {"x": 203,"y": 309,"on": true},
            {"x": 164,"y": 258,"on": true},
            {"x": 39,"y": 258,"on": true},
            {"x": 45,"y": 229,"on": true},
            {"x": 178,"y": 229,"on": true},
            {"x": 178,"y": 74,"on": true},
            {"x": 128,"y": 49,"on": false},
            {"x": 73,"y": 23,"on": false},
            {"x": 39,"y": 9,"on": true},
            {"x": 83,"y": -73,"on": true},
            {"x": 91,"y": -68,"on": false},
            {"x": 96,"y": -62,"on": false},
            {"x": 95,"y": -49,"on": true},
            {"x": 131,"y": -20,"on": false},
            {"x": 189,"y": 32,"on": false},
            {"x": 226,"y": 72,"on": true},
            {"x": 299,"y": -29,"on": false},
            {"x": 378,"y": -50,"on": false},
            {"x": 560,"y": -50,"on": true},
            {"x": 914,"y": -50,"on": true},
            {"x": 918,"y": -20,"on": false},
            {"x": 935,"y": -1,"on": false},
            {"x": 965,"y": 4,"on": true},
            {"x": 965,"y": 18,"on": true},
            {"x": 842,"y": 14,"on": false},
            {"x": 678,"y": 14,"on": false},
            {"x": 559,"y": 14,"on": true},
            {"x": 385,"y": 14,"on": false},
            {"x": 310,"y": 23,"on": false},
            {"x": 240,"y": 90,"on": true}
        ]
    ],
    "stemH": [],
    "stemV": [],
    "hintMasks": [
        {
            "contoursBefore": 0,
            "pointsBefore": 0,
            "maskH": [],
            "maskV": []
        }
    ],
    "contourMasks": [
        {
            "contoursBefore": 0,
            "pointsBefore": 0,
            "maskH": [false,false,false,false,false,false,false
            ],
            "maskV": [true,false,false,false,true
            ]
        },
        {
            "contoursBefore": 0,
            "pointsBefore": 0,
            "maskH": [true,false,false,true,false,true,false
            ],
            "maskV": [false,true,false,true,false
            ]
        }
    ],
    "CFF_fdSelect": "HKSerif-Regular-Ideographs"
}